rbds/__init__.py
rbds/__main__.py
rbds/monkey_patch.py
rbds/hook_utils/__init__.py
rbds/hook_utils/custom_config.py
rbds/hook_utils/dependencies.py
rbds-0.1.1.dist-info/LICENSE
rbds-0.1.1.dist-info/METADATA
rbds-0.1.1.dist-info/WHEEL
rbds-0.1.1.dist-info/entry_points.txt
rbds-0.1.1.dist-info/top_level.txt
rbds-0.1.1.dist-info/RECORD
