Metadata-Version: 2.2
Name: rbds
Version: 0.1.1
Summary: A library for cookiecutter data science with rebase tools
Author: Your Name
Author-email: "rebase.energy" <info@rebase.energy>
License: The MIT License (MIT)
Project-URL: homepage, https://github.com/rebase-energy/rebase-cookiecutter-data-science
Keywords: cookiecutter,data science,python
Classifier: Programming Language :: Python :: 3
Classifier: License :: OSI Approved :: MIT License
Classifier: Operating System :: OS Independent
Requires-Python: >=3.8
License-File: LICENSE
Requires-Dist: click
Requires-Dist: cookiecutter
Provides-Extra: dev
Requires-Dist: pytest; extra == "dev"
Requires-Dist: black; extra == "dev"
